Metadata-Version: 2.4
Name: iflow-mcp_mcp-email-server
Version: 0.0.5
Summary: IMAP and SMTP via MCP Server
Project-URL: Homepage, https://ai-zerolab.github.io/mcp-email-server/
Project-URL: Repository, https://github.com/ai-zerolab/mcp-email-server
Project-URL: Documentation, https://ai-zerolab.github.io/mcp-email-server/
Author-email: ai-zerolab <jizhongsheng957@gmail.com>
License-File: LICENSE
Keywords: IMAP,MCP,SMTP,email
Classifier: Intended Audience :: Developers
Classifier: Programming Language :: Python
Classifier: Programming Language :: Python :: 3
Classifier: Programming Language :: Python :: 3.10
Classifier: Programming Language :: Python :: 3.11
Classifier: Programming Language :: Python :: 3.12
Classifier: Programming Language :: Python :: 3.13
Classifier: Topic :: Software Development :: Libraries :: Python Modules
Requires-Python: <4.0,>=3.10
Requires-Dist: aioimaplib>=2.0.1
Requires-Dist: aiosmtplib==4.0.0
Requires-Dist: gradio>=5.18.0
Requires-Dist: jinja2>=3.1.5
Requires-Dist: loguru>=0.7.3
Requires-Dist: mcp[cli]>=1.3.0
Requires-Dist: pydantic-settings[toml]>=2.8.0
Requires-Dist: pydantic>=2.10.6
Requires-Dist: tomli-w>=1.2.0
Requires-Dist: typer>=0.15.1
